pip_install_test/__init__.py
pip_install_test-0.5.dist-info/METADATA
pip_install_test-0.5.dist-info/RECORD
pip_install_test-0.5.dist-info/WHEEL
pip_install_test-0.5.dist-info/top_level.txt
