Metadata-Version: 2.1
Name: pip-install-test
Version: 0.5
Summary: A minimal stub package to test success of pip install
Home-page: UNKNOWN
Author: Simon Krughoff
Author-email: krughoff@lsst.org
License: MIT
Platform: UNKNOWN
